r2midi-0.1.138.dist-info/licenses/LICENSE
r2midi_client/__init__.py
r2midi_client/__main__.py
r2midi_client/api_client.py
r2midi_client/config.py
r2midi_client/main.py
r2midi_client/models.py
r2midi_client/performance.py
r2midi_client/requirements.txt
r2midi_client/shortcuts.py
r2midi_client/test_colors.py
r2midi_client/themes.py
r2midi_client/ui/__init__.py
r2midi_client/ui/device_panel.py
r2midi_client/ui/edit_dialog.py
r2midi_client/ui/main_window.py
r2midi_client/ui/patch_panel.py
r2midi_client/ui/preferences_dialog.py
r2midi_client/ui/preset_panel.py
server/__init__.py
server/__main__.py
server/device_manager.py
server/git_operations.py
server/main.py
server/midi_utils.py
server/models.py
server/run_server.py
server/ui_launcher.py
server/version.py
server/midi-presets/.gitkeep
server/midi-presets/README.md
tests/README.md
tests/__init__.py
tests/temp/test_qtbot.py
tests/unit/__init__.py
tests/unit/r2midi_client/__init__.py
tests/unit/r2midi_client/test_api_client.py
tests/unit/r2midi_client/test_models.py
tests/unit/server/__init__.py
tests/unit/server/test_device_manager.py
tests/unit/server/test_main.py
tests/unit/server/test_midi_utils.py
tests/unit/server/test_models.py
tests/unit/server/test_ui_launcher.py
r2midi-0.1.138.dist-info/METADATA
r2midi-0.1.138.dist-info/WHEEL
r2midi-0.1.138.dist-info/top_level.txt
r2midi-0.1.138.dist-info/RECORD
