Metadata-Version: 2.4
Name: r2midi
Version: 0.1.138
Summary: MIDI 2.0 Patch Selection Application
Author-email: R2MIDI Team <example@example.com>
License: MIT
Project-URL: Homepage, https://github.com/tirans/r2midi
Project-URL: Bug Tracker, https://github.com/tirans/r2midi/issues
Classifier: Programming Language :: Python :: 3
Classifier: Operating System :: OS Independent
Requires-Python: >=3.9,<3.13
License-File: LICENSE
Requires-Dist: fastapi>=0.104.0
Requires-Dist: uvicorn>=0.23.2
Requires-Dist: pydantic>=2.4.2
Requires-Dist: python-rtmidi>=1.5.5
Requires-Dist: mido>=1.3.0
Requires-Dist: pyqt6>=6.5.2
Requires-Dist: httpx>=0.25.0
Requires-Dist: python-dotenv>=1.0.0
Requires-Dist: black>=24.8.0
Requires-Dist: GitPython>=3.1.40
Requires-Dist: psutil>=7.0.0
Provides-Extra: test
Requires-Dist: pytest>=7.4.0; extra == "test"
Requires-Dist: pytest-asyncio>=0.21.1; extra == "test"
Requires-Dist: pytest-mock>=3.11.1; extra == "test"
Requires-Dist: pytest-cov>=4.1.0; extra == "test"
Requires-Dist: httpx>=0.25.0; extra == "test"
Provides-Extra: dev
Requires-Dist: briefcase>=0.3.21; extra == "dev"
Requires-Dist: black>=24.8.0; extra == "dev"
Requires-Dist: flake8>=7.0.0; extra == "dev"
Requires-Dist: pre-commit>=3.0.0; extra == "dev"
Dynamic: license-file
Dynamic: requires-python
